sourmash_plugin_tables.py
sourmash_plugin_tables-0.7.dist-info/licenses/LICENSE
sourmash_plugin_tables-0.7.dist-info/METADATA
sourmash_plugin_tables-0.7.dist-info/WHEEL
sourmash_plugin_tables-0.7.dist-info/entry_points.txt
sourmash_plugin_tables-0.7.dist-info/top_level.txt
sourmash_plugin_tables-0.7.dist-info/RECORD
