Metadata-Version: 2.4
Name: sourmash_plugin_tables
Version: 0.7
Summary: sourmash plugin to do tables.
Requires-Python: >=3.10
License-File: LICENSE
Requires-Dist: sourmash<5,>=4.8.11
Requires-Dist: polars
Requires-Dist: sourmash_utils
Dynamic: license-file
